qiskit_rng/VERSION.txt
qiskit_rng/__init__.py
qiskit_rng/constants.py
qiskit_rng/exceptions.py
qiskit_rng/generator.py
qiskit_rng/generator_job.py
qiskit_rng/generator_result.py
qiskit_rng/model.py
qiskit_rng/utils.py
qiskit_rng-0.2.2.dist-info/LICENSE.txt
qiskit_rng-0.2.2.dist-info/METADATA
qiskit_rng-0.2.2.dist-info/WHEEL
qiskit_rng-0.2.2.dist-info/top_level.txt
qiskit_rng-0.2.2.dist-info/RECORD
