Metadata-Version: 2.1
Name: qiskit-rng
Version: 0.2.2
Summary: Qiskit Random Number Generator.
Home-page: https://github.com/qiskit-community/qiskit_rng
Author: Qiskit Development Team
Author-email: hello@qiskit.org
License: Apache 2.0
Project-URL: Bug Tracker, https://github.com/qiskit-community/qiskit_rng/issues
Project-URL: Documentation, https://qiskit-rng.readthedocs.io
Project-URL: Source Code, https://github.com/qiskit-community/qiskit_rng
Keywords: qiskit quantum cqc qrng
Platform: UNKNOWN
Classifier: Environment :: Console
Classifier: License :: OSI Approved :: Apache Software License
Classifier: Intended Audience :: Developers
Classifier: Intended Audience :: Science/Research
Classifier: Operating System :: Microsoft :: Windows
Classifier: Operating System :: MacOS
Classifier: Operating System :: POSIX :: Linux
Classifier: Programming Language :: Python :: 3 :: Only
Classifier: Programming Language :: Python :: 3.6
Classifier: Programming Language :: Python :: 3.7
Classifier: Programming Language :: Python :: 3.8
Classifier: Topic :: Scientific/Engineering
Requires-Python: >=3.6
Requires-Dist: qiskit-ibmq-provider (>=0.10)
Requires-Dist: qiskit-terra (>=0.16.2)
